BinaryTree/__init__.py
BinaryTree/tree.py
biNNytree-0.1.1.dist-info/METADATA
biNNytree-0.1.1.dist-info/WHEEL
biNNytree-0.1.1.dist-info/top_level.txt
biNNytree-0.1.1.dist-info/RECORD
