Metadata-Version: 2.1
Name: biNNytree
Version: 0.1.1
Summary: Binary Tree Beauty Printer
Author: Abraham
Author-email: ibrohimjon.ismoilov.007@gmail.com
Keywords: Tree,Binary,Binary Tree,Beauty print,Beauty Binary Tree
Classifier: Development Status :: 4 - Beta
Classifier: Intended Audience :: Developers
Classifier: Programming Language :: Python :: 3
Classifier: Operating System :: Unix
Classifier: Operating System :: MacOS :: MacOS X
Classifier: Operating System :: Microsoft :: Windows
